examples/prssine/prsgen8.v
module prsgen8 (clk, rst, compare, out);
    input clk, rst;
    input [8:1] compare;
    output reg out;
    
    reg [8:1] sr;
        
    always @(posedge clk)
    begin
        if (rst) begin
            sr  <= 8'b10101010;
            out <= 0;
        end
        else begin
            sr[8:2] <= sr[7:1];
            sr[1]   <= sr[4] ^ sr[5] ^ sr[6] ^ sr[8];            
            out     <= (compare >= sr);
        end
    end
endmodule

examples/prssine/prsgen8_tb.v
module prsgen8_tb;
    reg reset = 0;
    reg clk = 0;
    wire out;

    /* Make a reset pulse and specify dump file */
    initial begin
        $dumpfile("prsgen8_tb.vcd");
        $dumpvars(0, prsgen8_tb);

        # 0 reset = 1;
        # 2 reset = 0;
        # 1024 $finish;
    end

    /* Make a regular pulsing clock. */
    always #1 clk = !clk;

    prsgen8 prs(clk, reset, 8'h80, out);
endmodule

examples/prssine/prsgen8_tb.vcd
$date
	Mon Mar 20 05:57:16 2017
$end
$version
	Icarus Verilog
$end
$timescale
	1s
$end
$scope module prsgen8_tb $end
$var wire 1 ! out $end
$var reg 1 " clk $end
$var reg 1 # reset $end
$scope module prs $end
$var wire 1 " clk $end
$var wire 8 $ compare [8:1] $end
$var wire 1 # rst $end
$var reg 1 ! out $end
$var reg 8 % sr [8:1] $end
$upscope $end
$upscope $end
$enddefinitions $end
#0
$dumpvars
bx %
b10000000 $
1#
0"
x!
$end
#1
0!
b10101010 %
1"
#2
0"
0#
#3
b1010101 %
1"
#4
0"
#5
1!
b10101011 %
1"
#6
0"
#7
0!
b1010111 %
1"
#8
0"
#9
1!
b10101111 %
1"
#10
0"
#11
0!
b1011111 %
1"
#12
0"
#13
1!
b10111110 %
1"
#14
0"
#15
0!
b1111100 %
1"
#16
0"
#17
1!
b11111001 %
1"
#18
0"
#19
0!
b11110010 %
1"
#20
0"
#21
b11100101 %
1"
#22
0"
#23
b11001010 %
1"
#24
0"
#25
b10010100 %
1"
#26
0"
#27
b101000 %
1"
#28
0"
#29
1!
b1010000 %
1"
#30
0"
#31
b10100001 %
1"
#32
0"
#33
0!
b1000010 %
1"
#34
0"
#35
1!
b10000100 %
1"
#36
0"
#37
0!
b1001 %
1"
#38
0"
#39
1!
b10011 %
1"
#40
0"
#41
b100111 %
1"
#42
0"
#43
b1001111 %
1"
#44
0"
#45
b10011111 %
1"
#46
0"
#47
0!
b111111 %
1"
#48
0"
#49
1!
b1111111 %
1"
#50
0"
#51
b11111111 %
1"
#52
0"
#53
0!
b11111110 %
1"
#54
0"
#55
b11111100 %
1"
#56
0"
#57
b11111000 %
1"
#58
0"
#59
b11110000 %
1"
#60
0"
#61
b11100001 %
1"
#62
0"
#63
b11000010 %
1"
#64
0"
#65
b10000101 %
1"
#66
0"
#67
b1011 %
1"
#68
0"
#69
1!
b10111 %
1"
#70
0"
#71
b101111 %
1"
#72
0"
#73
b1011110 %
1"
#74
0"
#75
b10111100 %
1"
#76
0"
#77
0!
b1111000 %
1"
#78
0"
#79
1!
b11110001 %
1"
#80
0"
#81
0!
b11100011 %
1"
#82
0"
#83
b11000110 %
1"
#84
0"
#85
b10001101 %
1"
#86
0"
#87
b11010 %
1"
#88
0"
#89
1!
b110100 %
1"
#90
0"
#91
b1101000 %
1"
#92
0"
#93
b11010000 %
1"
#94
0"
#95
0!
b10100000 %
1"
#96
0"
#97
b1000000 %
1"
#98
0"
#99
1!
b10000000 %
1"
#100
0"
#101
b1 %
1"
#102
0"
#103
b10 %
1"
#104
0"
#105
b100 %
1"
#106
0"
#107
b1000 %
1"
#108
0"
#109
b10001 %
1"
#110
0"
#111
b100011 %
1"
#112
0"
#113
b1000111 %
1"
#114
0"
#115
b10001110 %
1"
#116
0"
#117
0!
b11100 %
1"
#118
0"
#119
1!
b111000 %
1"
#120
0"
#121
b1110001 %
1"
#122
0"
#123
b11100010 %
1"
#124
0"
#125
0!
b11000100 %
1"
#126
0"
#127
b10001001 %
1"
#128
0"
#129
b10010 %
1"
#130
0"
#131
1!
b100101 %
1"
#132
0"
#133
b1001011 %
1"
#134
0"
#135
b10010111 %
1"
#136
0"
#137
0!
b101110 %
1"
#138
0"
#139
1!
b1011100 %
1"
#140
0"
#141
b10111000 %
1"
#142
0"
#143
0!
b1110000 %
1"
#144
0"
#145
1!
b11100000 %
1"
#146
0"
#147
0!
b11000000 %
1"
#148
0"
#149
b10000001 %
1"
#150
0"
#151
b11 %
1"
#152
0"
#153
1!
b110 %
1"
#154
0"
#155
b1100 %
1"
#156
0"
#157
b11001 %
1"
#158
0"
#159
b110010 %
1"
#160
0"
#161
b1100100 %
1"
#162
0"
#163
b11001001 %
1"
#164
0"
#165
0!
b10010010 %
1"
#166
0"
#167
b100100 %
1"
#168
0"
#169
1!
b1001001 %
1"
#170
0"
#171
b10010011 %
1"
#172
0"
#173
0!
b100110 %
1"
#174
0"
#175
1!
b1001101 %
1"
#176
0"
#177
b10011011 %
1"
#178
0"
#179
0!
b110111 %
1"
#180
0"
#181
1!
b1101110 %
1"
#182
0"
#183
b11011100 %
1"
#184
0"
#185
0!
b10111001 %
1"
#186
0"
#187
b1110010 %
1"
#188
0"
#189
1!
b11100100 %
1"
#190
0"
#191
0!
b11001000 %
1"
#192
0"
#193
b10010000 %
1"
#194
0"
#195
b100000 %
1"
#196
0"
#197
1!
b1000001 %
1"
#198
0"
#199
b10000010 %
1"
#200
0"
#201
0!
b101 %
1"
#202
0"
#203
1!
b1010 %
1"
#204
0"
#205
b10101 %
1"
#206
0"
#207
b101011 %
1"
#208
0"
#209
b1010110 %
1"
#210
0"
#211
b10101101 %
1"
#212
0"
#213
0!
b1011011 %
1"
#214
0"
#215
1!
b10110110 %
1"
#216
0"
#217
0!
b1101101 %
1"
#218
0"
#219
1!
b11011010 %
1"
#220
0"
#221
0!
b10110101 %
1"
#222
0"
#223
b1101011 %
1"
#224
0"
#225
1!
b11010110 %
1"
#226
0"
#227
0!
b10101100 %
1"
#228
0"
#229
b1011001 %
1"
#230
0"
#231
1!
b10110010 %
1"
#232
0"
#233
0!
b1100101 %
1"
#234
0"
#235
1!
b11001011 %
1"
#236
0"
#237
0!
b10010110 %
1"
#238
0"
#239
b101100 %
1"
#240
0"
#241
1!
b1011000 %
1"
#242
0"
#243
b10110000 %
1"
#244
0"
#245
0!
b1100001 %
1"
#246
0"
#247
1!
b11000011 %
1"
#248
0"
#249
0!
b10000111 %
1"
#250
0"
#251
b1111 %
1"
#252
0"
#253
1!
b11111 %
1"
#254
0"
#255
b111110 %
1"
#256
0"
#257
b1111101 %
1"
#258
0"
#259
b11111011 %
1"
#260
0"
#261
0!
b11110110 %
1"
#262
0"
#263
b11101101 %
1"
#264
0"
#265
b11011011 %
1"
#266
0"
#267
b10110111 %
1"
#268
0"
#269
b1101111 %
1"
#270
0"
#271
1!
b11011110 %
1"
#272
0"
#273
0!
b10111101 %
1"
#274
0"
#275
b1111010 %
1"
#276
0"
#277
1!
b11110101 %
1"
#278
0"
#279
0!
b11101011 %
1"
#280
0"
#281
b11010111 %
1"
#282
0"
#283
b10101110 %
1"
#284
0"
#285
b1011101 %
1"
#286
0"
#287
1!
b10111010 %
1"
#288
0"
#289
0!
b1110100 %
1"
#290
0"
#291
1!
b11101000 %
1"
#292
0"
#293
0!
b11010001 %
1"
#294
0"
#295
b10100010 %
1"
#296
0"
#297
b1000100 %
1"
#298
0"
#299
1!
b10001000 %
1"
#300
0"
#301
0!
b10000 %
1"
#302
0"
#303
1!
b100001 %
1"
#304
0"
#305
b1000011 %
1"
#306
0"
#307
b10000110 %
1"
#308
0"
#309
0!
b1101 %
1"
#310
0"
#311
1!
b11011 %
1"
#312
0"
#313
b110110 %
1"
#314
0"
#315
b1101100 %
1"
#316
0"
#317
b11011000 %
1"
#318
0"
#319
0!
b10110001 %
1"
#320
0"
#321
b1100011 %
1"
#322
0"
#323
1!
b11000111 %
1"
#324
0"
#325
0!
b10001111 %
1"
#326
0"
#327
b11110 %
1"
#328
0"
#329
1!
b111100 %
1"
#330
0"
#331
b1111001 %
1"
#332
0"
#333
b11110011 %
1"
#334
0"
#335
0!
b11100111 %
1"
#336
0"
#337
b11001110 %
1"
#338
0"
#339
b10011100 %
1"
#340
0"
#341
b111001 %
1"
#342
0"
#343
1!
b1110011 %
1"
#344
0"
#345
b11100110 %
1"
#346
0"
#347
0!
b11001100 %
1"
#348
0"
#349
b10011000 %
1"
#350
0"
#351
b110001 %
1"
#352
0"
#353
1!
b1100010 %
1"
#354
0"
#355
b11000101 %
1"
#356
0"
#357
0!
b10001011 %
1"
#358
0"
#359
b10110 %
1"
#360
0"
#361
1!
b101101 %
1"
#362
0"
#363
b1011010 %
1"
#364
0"
#365
b10110100 %
1"
#366
0"
#367
0!
b1101001 %
1"
#368
0"
#369
1!
b11010010 %
1"
#370
0"
#371
0!
b10100100 %
1"
#372
0"
#373
b1001000 %
1"
#374
0"
#375
1!
b10010001 %
1"
#376
0"
#377
0!
b100010 %
1"
#378
0"
#379
1!
b1000101 %
1"
#380
0"
#381
b10001010 %
1"
#382
0"
#383
0!
b10100 %
1"
#384
0"
#385
1!
b101001 %
1"
#386
0"
#387
b1010010 %
1"
#388
0"
#389
b10100101 %
1"
#390
0"
#391
0!
b1001010 %
1"
#392
0"
#393
1!
b10010101 %
1"
#394
0"
#395
0!
b101010 %
1"
#396
0"
#397
1!
b1010100 %
1"
#398
0"
#399
b10101001 %
1"
#400
0"
#401
0!
b1010011 %
1"
#402
0"
#403
1!
b10100111 %
1"
#404
0"
#405
0!
b1001110 %
1"
#406
0"
#407
1!
b10011101 %
1"
#408
0"
#409
0!
b111011 %
1"
#410
0"
#411
1!
b1110111 %
1"
#412
0"
#413
b11101110 %
1"
#414
0"
#415
0!
b11011101 %
1"
#416
0"
#417
b10111011 %
1"
#418
0"
#419
b1110110 %
1"
#420
0"
#421
1!
b11101100 %
1"
#422
0"
#423
0!
b11011001 %
1"
#424
0"
#425
b10110011 %
1"
#426
0"
#427
b1100111 %
1"
#428
0"
#429
1!
b11001111 %
1"
#430
0"
#431
0!
b10011110 %
1"
#432
0"
#433
b111101 %
1"
#434
0"
#435
1!
b1111011 %
1"
#436
0"
#437
b11110111 %
1"
#438
0"
#439
0!
b11101111 %
1"
#440
0"
#441
b11011111 %
1"
#442
0"
#443
b10111111 %
1"
#444
0"
#445
b1111110 %
1"
#446
0"
#447
1!
b11111101 %
1"
#448
0"
#449
0!
b11111010 %
1"
#450
0"
#451
b11110100 %
1"
#452
0"
#453
b11101001 %
1"
#454
0"
#455
b11010011 %
1"
#456
0"
#457
b10100110 %
1"
#458
0"
#459
b1001100 %
1"
#460
0"
#461
1!
b10011001 %
1"
#462
0"
#463
0!
b110011 %
1"
#464
0"
#465
1!
b1100110 %
1"
#466
0"
#467
b11001101 %
1"
#468
0"
#469
0!
b10011010 %
1"
#470
0"
#471
b110101 %
1"
#472
0"
#473
1!
b1101010 %
1"
#474
0"
#475
b11010100 %
1"
#476
0"
#477
0!
b10101000 %
1"
#478
0"
#479
b1010001 %
1"
#480
0"
#481
1!
b10100011 %
1"
#482
0"
#483
0!
b1000110 %
1"
#484
0"
#485
1!
b10001100 %
1"
#486
0"
#487
0!
b11000 %
1"
#488
0"
#489
1!
b110000 %
1"
#490
0"
#491
b1100000 %
1"
#492
0"
#493
b11000001 %
1"
#494
0"
#495
0!
b10000011 %
1"
#496
0"
#497
b111 %
1"
#498
0"
#499
1!
b1110 %
1"
#500
0"
#501
b11101 %
1"
#502
0"
#503
b111010 %
1"
#504
0"
#505
b1110101 %
1"
#506
0"
#507
b11101010 %
1"
#508
0"
#509
0!
b11010101 %
1"
#510
0"
#511
b10101010 %
1"
#512
0"
#513
b1010101 %
1"
#514
0"
#515
1!
b10101011 %
1"
#516
0"
#517
0!
b1010111 %
1"
#518
0"
#519
1!
b10101111 %
1"
#520
0"
#521
0!
b1011111 %
1"
#522
0"
#523
1!
b10111110 %
1"
#524
0"
#525
0!
b1111100 %
1"
#526
0"
#527
1!
b11111001 %
1"
#528
0"
#529
0!
b11110010 %
1"
#530
0"
#531
b11100101 %
1"
#532
0"
#533
b11001010 %
1"
#534
0"
#535
b10010100 %
1"
#536
0"
#537
b101000 %
1"
#538
0"
#539
1!
b1010000 %
1"
#540
0"
#541
b10100001 %
1"
#542
0"
#543
0!
b1000010 %
1"
#544
0"
#545
1!
b10000100 %
1"
#546
0"
#547
0!
b1001 %
1"
#548
0"
#549
1!
b10011 %
1"
#550
0"
#551
b100111 %
1"
#552
0"
#553
b1001111 %
1"
#554
0"
#555
b10011111 %
1"
#556
0"
#557
0!
b111111 %
1"
#558
0"
#559
1!
b1111111 %
1"
#560
0"
#561
b11111111 %
1"
#562
0"
#563
0!
b11111110 %
1"
#564
0"
#565
b11111100 %
1"
#566
0"
#567
b11111000 %
1"
#568
0"
#569
b11110000 %
1"
#570
0"
#571
b11100001 %
1"
#572
0"
#573
b11000010 %
1"
#574
0"
#575
b10000101 %
1"
#576
0"
#577
b1011 %
1"
#578
0"
#579
1!
b10111 %
1"
#580
0"
#581
b101111 %
1"
#582
0"
#583
b1011110 %
1"
#584
0"
#585
b10111100 %
1"
#586
0"
#587
0!
b1111000 %
1"
#588
0"
#589
1!
b11110001 %
1"
#590
0"
#591
0!
b11100011 %
1"
#592
0"
#593
b11000110 %
1"
#594
0"
#595
b10001101 %
1"
#596
0"
#597
b11010 %
1"
#598
0"
#599
1!
b110100 %
1"
#600
0"
#601
b1101000 %
1"
#602
0"
#603
b11010000 %
1"
#604
0"
#605
0!
b10100000 %
1"
#606
0"
#607
b1000000 %
1"
#608
0"
#609
1!
b10000000 %
1"
#610
0"
#611
b1 %
1"
#612
0"
#613
b10 %
1"
#614
0"
#615
b100 %
1"
#616
0"
#617
b1000 %
1"
#618
0"
#619
b10001 %
1"
#620
0"
#621
b100011 %
1"
#622
0"
#623
b1000111 %
1"
#624
0"
#625
b10001110 %
1"
#626
0"
#627
0!
b11100 %
1"
#628
0"
#629
1!
b111000 %
1"
#630
0"
#631
b1110001 %
1"
#632
0"
#633
b11100010 %
1"
#634
0"
#635
0!
b11000100 %
1"
#636
0"
#637
b10001001 %
1"
#638
0"
#639
b10010 %
1"
#640
0"
#641
1!
b100101 %
1"
#642
0"
#643
b1001011 %
1"
#644
0"
#645
b10010111 %
1"
#646
0"
#647
0!
b101110 %
1"
#648
0"
#649
1!
b1011100 %
1"
#650
0"
#651
b10111000 %
1"
#652
0"
#653
0!
b1110000 %
1"
#654
0"
#655
1!
b11100000 %
1"
#656
0"
#657
0!
b11000000 %
1"
#658
0"
#659
b10000001 %
1"
#660
0"
#661
b11 %
1"
#662
0"
#663
1!
b110 %
1"
#664
0"
#665
b1100 %
1"
#666
0"
#667
b11001 %
1"
#668
0"
#669
b110010 %
1"
#670
0"
#671
b1100100 %
1"
#672
0"
#673
b11001001 %
1"
#674
0"
#675
0!
b10010010 %
1"
#676
0"
#677
b100100 %
1"
#678
0"
#679
1!
b1001001 %
1"
#680
0"
#681
b10010011 %
1"
#682
0"
#683
0!
b100110 %
1"
#684
0"
#685
1!
b1001101 %
1"
#686
0"
#687
b10011011 %
1"
#688
0"
#689
0!
b110111 %
1"
#690
0"
#691
1!
b1101110 %
1"
#692
0"
#693
b11011100 %
1"
#694
0"
#695
0!
b10111001 %
1"
#696
0"
#697
b1110010 %
1"
#698
0"
#699
1!
b11100100 %
1"
#700
0"
#701
0!
b11001000 %
1"
#702
0"
#703
b10010000 %
1"
#704
0"
#705
b100000 %
1"
#706
0"
#707
1!
b1000001 %
1"
#708
0"
#709
b10000010 %
1"
#710
0"
#711
0!
b101 %
1"
#712
0"
#713
1!
b1010 %
1"
#714
0"
#715
b10101 %
1"
#716
0"
#717
b101011 %
1"
#718
0"
#719
b1010110 %
1"
#720
0"
#721
b10101101 %
1"
#722
0"
#723
0!
b1011011 %
1"
#724
0"
#725
1!
b10110110 %
1"
#726
0"
#727
0!
b1101101 %
1"
#728
0"
#729
1!
b11011010 %
1"
#730
0"
#731
0!
b10110101 %
1"
#732
0"
#733
b1101011 %
1"
#734
0"
#735
1!
b11010110 %
1"
#736
0"
#737
0!
b10101100 %
1"
#738
0"
#739
b1011001 %
1"
#740
0"
#741
1!
b10110010 %
1"
#742
0"
#743
0!
b1100101 %
1"
#744
0"
#745
1!
b11001011 %
1"
#746
0"
#747
0!
b10010110 %
1"
#748
0"
#749
b101100 %
1"
#750
0"
#751
1!
b1011000 %
1"
#752
0"
#753
b10110000 %
1"
#754
0"
#755
0!
b1100001 %
1"
#756
0"
#757
1!
b11000011 %
1"
#758
0"
#759
0!
b10000111 %
1"
#760
0"
#761
b1111 %
1"
#762
0"
#763
1!
b11111 %
1"
#764
0"
#765
b111110 %
1"
#766
0"
#767
b1111101 %
1"
#768
0"
#769
b11111011 %
1"
#770
0"
#771
0!
b11110110 %
1"
#772
0"
#773
b11101101 %
1"
#774
0"
#775
b11011011 %
1"
#776
0"
#777
b10110111 %
1"
#778
0"
#779
b1101111 %
1"
#780
0"
#781
1!
b11011110 %
1"
#782
0"
#783
0!
b10111101 %
1"
#784
0"
#785
b1111010 %
1"
#786
0"
#787
1!
b11110101 %
1"
#788
0"
#789
0!
b11101011 %
1"
#790
0"
#791
b11010111 %
1"
#792
0"
#793
b10101110 %
1"
#794
0"
#795
b1011101 %
1"
#796
0"
#797
1!
b10111010 %
1"
#798
0"
#799
0!
b1110100 %
1"
#800
0"
#801
1!
b11101000 %
1"
#802
0"
#803
0!
b11010001 %
1"
#804
0"
#805
b10100010 %
1"
#806
0"
#807
b1000100 %
1"
#808
0"
#809
1!
b10001000 %
1"
#810
0"
#811
0!
b10000 %
1"
#812
0"
#813
1!
b100001 %
1"
#814
0"
#815
b1000011 %
1"
#816
0"
#817
b10000110 %
1"
#818
0"
#819
0!
b1101 %
1"
#820
0"
#821
1!
b11011 %
1"
#822
0"
#823
b110110 %
1"
#824
0"
#825
b1101100 %
1"
#826
0"
#827
b11011000 %
1"
#828
0"
#829
0!
b10110001 %
1"
#830
0"
#831
b1100011 %
1"
#832
0"
#833
1!
b11000111 %
1"
#834
0"
#835
0!
b10001111 %
1"
#836
0"
#837
b11110 %
1"
#838
0"
#839
1!
b111100 %
1"
#840
0"
#841
b1111001 %
1"
#842
0"
#843
b11110011 %
1"
#844
0"
#845
0!
b11100111 %
1"
#846
0"
#847
b11001110 %
1"
#848
0"
#849
b10011100 %
1"
#850
0"
#851
b111001 %
1"
#852
0"
#853
1!
b1110011 %
1"
#854
0"
#855
b11100110 %
1"
#856
0"
#857
0!
b11001100 %
1"
#858
0"
#859
b10011000 %
1"
#860
0"
#861
b110001 %
1"
#862
0"
#863
1!
b1100010 %
1"
#864
0"
#865
b11000101 %
1"
#866
0"
#867
0!
b10001011 %
1"
#868
0"
#869
b10110 %
1"
#870
0"
#871
1!
b101101 %
1"
#872
0"
#873
b1011010 %
1"
#874
0"
#875
b10110100 %
1"
#876
0"
#877
0!
b1101001 %
1"
#878
0"
#879
1!
b11010010 %
1"
#880
0"
#881
0!
b10100100 %
1"
#882
0"
#883
b1001000 %
1"
#884
0"
#885
1!
b10010001 %
1"
#886
0"
#887
0!
b100010 %
1"
#888
0"
#889
1!
b1000101 %
1"
#890
0"
#891
b10001010 %
1"
#892
0"
#893
0!
b10100 %
1"
#894
0"
#895
1!
b101001 %
1"
#896
0"
#897
b1010010 %
1"
#898
0"
#899
b10100101 %
1"
#900
0"
#901
0!
b1001010 %
1"
#902
0"
#903
1!
b10010101 %
1"
#904
0"
#905
0!
b101010 %
1"
#906
0"
#907
1!
b1010100 %
1"
#908
0"
#909
b10101001 %
1"
#910
0"
#911
0!
b1010011 %
1"
#912
0"
#913
1!
b10100111 %
1"
#914
0"
#915
0!
b1001110 %
1"
#916
0"
#917
1!
b10011101 %
1"
#918
0"
#919
0!
b111011 %
1"
#920
0"
#921
1!
b1110111 %
1"
#922
0"
#923
b11101110 %
1"
#924
0"
#925
0!
b11011101 %
1"
#926
0"
#927
b10111011 %
1"
#928
0"
#929
b1110110 %
1"
#930
0"
#931
1!
b11101100 %
1"
#932
0"
#933
0!
b11011001 %
1"
#934
0"
#935
b10110011 %
1"
#936
0"
#937
b1100111 %
1"
#938
0"
#939
1!
b11001111 %
1"
#940
0"
#941
0!
b10011110 %
1"
#942
0"
#943
b111101 %
1"
#944
0"
#945
1!
b1111011 %
1"
#946
0"
#947
b11110111 %
1"
#948
0"
#949
0!
b11101111 %
1"
#950
0"
#951
b11011111 %
1"
#952
0"
#953
b10111111 %
1"
#954
0"
#955
b1111110 %
1"
#956
0"
#957
1!
b11111101 %
1"
#958
0"
#959
0!
b11111010 %
1"
#960
0"
#961
b11110100 %
1"
#962
0"
#963
b11101001 %
1"
#964
0"
#965
b11010011 %
1"
#966
0"
#967
b10100110 %
1"
#968
0"
#969
b1001100 %
1"
#970
0"
#971
1!
b10011001 %
1"
#972
0"
#973
0!
b110011 %
1"
#974
0"
#975
1!
b1100110 %
1"
#976
0"
#977
b11001101 %
1"
#978
0"
#979
0!
b10011010 %
1"
#980
0"
#981
b110101 %
1"
#982
0"
#983
1!
b1101010 %
1"
#984
0"
#985
b11010100 %
1"
#986
0"
#987
0!
b10101000 %
1"
#988
0"
#989
b1010001 %
1"
#990
0"
#991
1!
b10100011 %
1"
#992
0"
#993
0!
b1000110 %
1"
#994
0"
#995
1!
b10001100 %
1"
#996
0"
#997
0!
b11000 %
1"
#998
0"
#999
1!
b110000 %
1"
#1000
0"
#1001
b1100000 %
1"
#1002
0"
#1003
b11000001 %
1"
#1004
0"
#1005
0!
b10000011 %
1"
#1006
0"
#1007
b111 %
1"
#1008
0"
#1009
1!
b1110 %
1"
#1010
0"
#1011
b11101 %
1"
#1012
0"
#1013
b111010 %
1"
#1014
0"
#1015
b1110101 %
1"
#1016
0"
#1017
b11101010 %
1"
#1018
0"
#1019
0!
b11010101 %
1"
#1020
0"
#1021
b10101010 %
1"
#1022
0"
#1023
b1010101 %
1"
#1024
0"
#1025
1!
b10101011 %
1"
